open_flags/__init__.py
open_flags/flag_functions.py
open_flags/flag_map.py
open_flags/generate_flag_map.py
open_flags/flags/brazil/acre.svg
open_flags/flags/brazil/alagoas.svg
open_flags/flags/brazil/amapá.svg
open_flags/flags/brazil/amazonas.svg
open_flags/flags/brazil/bahia.svg
open_flags/flags/brazil/brazil.svg
open_flags/flags/brazil/ceará.svg
open_flags/flags/brazil/distrito-federal.svg
open_flags/flags/brazil/espírito-santo.svg
open_flags/flags/brazil/estado-rio-de-janeiro.svg
open_flags/flags/brazil/goiás.svg
open_flags/flags/brazil/maranhão.svg
open_flags/flags/brazil/mato-grosso-do-sul.svg
open_flags/flags/brazil/mato-grosso.svg
open_flags/flags/brazil/minas-gerais.svg
open_flags/flags/brazil/paraná.svg
open_flags/flags/brazil/paraíba.svg
open_flags/flags/brazil/pará.svg
open_flags/flags/brazil/pernambuco.svg
open_flags/flags/brazil/piauí.svg
open_flags/flags/brazil/rio-grande-do-norte.svg
open_flags/flags/brazil/rio-grande-do-sul.svg
open_flags/flags/brazil/rondônia.svg
open_flags/flags/brazil/roraima.svg
open_flags/flags/brazil/santa-catarina.svg
open_flags/flags/brazil/sergipe.svg
open_flags/flags/brazil/são-paulo.svg
open_flags/flags/brazil/tocantins.svg
open_flags/flags/canada/alberta.svg
open_flags/flags/canada/british-columbia.svg
open_flags/flags/canada/canada.svg
open_flags/flags/canada/governor-general-of-canada.svg
open_flags/flags/canada/manitoba.svg
open_flags/flags/canada/new-brunswick.svg
open_flags/flags/canada/newfoundland-and-labrador.svg
open_flags/flags/canada/northwest-territories.svg
open_flags/flags/canada/nova-scotia.svg
open_flags/flags/canada/nunavut.svg
open_flags/flags/canada/ontario.svg
open_flags/flags/canada/prince-edward-island.svg
open_flags/flags/canada/quebec.svg
open_flags/flags/canada/royal-standard-members-canadian-royal-family.svg
open_flags/flags/canada/saskatchewan.svg
open_flags/flags/canada/yukon.svg
open_flags/flags/england/bedfordshire.svg
open_flags/flags/england/berkshire.svg
open_flags-0.0.2.dist-info/METADATA
open_flags-0.0.2.dist-info/WHEEL
open_flags-0.0.2.dist-info/top_level.txt
open_flags-0.0.2.dist-info/RECORD
